LICENSE
MANIFEST.in
README.rst
requirements.txt
setup.py
discord4py/__init__.py
discord4py/__main__.py
discord4py/abc.py
discord4py/activity.py
discord4py/appinfo.py
discord4py/asset.py
discord4py/audit_logs.py
discord4py/backoff.py
discord4py/channel.py
discord4py/client.py
discord4py/colour.py
discord4py/components.py
discord4py/context_managers.py
discord4py/embeds.py
discord4py/emoji.py
discord4py/enums.py
discord4py/errors.py
discord4py/file.py
discord4py/flags.py
discord4py/gateway.py
discord4py/guild.py
discord4py/http.py
discord4py/integrations.py
discord4py/interactions.py
discord4py/invite.py
discord4py/iterators.py
discord4py/member.py
discord4py/mentions.py
discord4py/message.py
discord4py/mixins.py
discord4py/object.py
discord4py/oggparse.py
discord4py/opus.py
discord4py/partial_emoji.py
discord4py/permissions.py
discord4py/player.py
discord4py/py.typed
discord4py/raw_models.py
discord4py/reaction.py
discord4py/role.py
discord4py/shard.py
discord4py/stage_instance.py
discord4py/state.py
discord4py/sticker.py
discord4py/team.py
discord4py/template.py
discord4py/threads.py
discord4py/user.py
discord4py/utils.py
discord4py/voice_client.py
discord4py/widget.py
discord4py.egg-info/PKG-INFO
discord4py.egg-info/SOURCES.txt
discord4py.egg-info/dependency_links.txt
discord4py.egg-info/requires.txt
discord4py.egg-info/top_level.txt
discord4py/bin/libopus-0.x64.dll
discord4py/bin/libopus-0.x86.dll
discord4py/ext/commands/__init__.py
discord4py/ext/commands/_types.py
discord4py/ext/commands/bot.py
discord4py/ext/commands/cog.py
discord4py/ext/commands/context.py
discord4py/ext/commands/converter.py
discord4py/ext/commands/cooldowns.py
discord4py/ext/commands/core.py
discord4py/ext/commands/errors.py
discord4py/ext/commands/flags.py
discord4py/ext/commands/help.py
discord4py/ext/commands/view.py
discord4py/ext/tasks/__init__.py
discord4py/types/__init__.py
discord4py/types/activity.py
discord4py/types/appinfo.py
discord4py/types/audit_log.py
discord4py/types/channel.py
discord4py/types/components.py
discord4py/types/embed.py
discord4py/types/emoji.py
discord4py/types/gateway.py
discord4py/types/guild.py
