Metadata-Version: 2.1
Name: discord4py
Version: 1.0.5
Summary: A Python wrapper for the Discord API
Home-page: https://github.com/palmtrww69/Discord4Py
Author: palmtrww
License: MIT
Project-URL: Issue tracker, https://github.com/palmtrww69/Discord4Py/issues
Project-URL: Documentation, https://discordpy.readthedocs.io/en/latest/
Platform: UNKNOWN
Classifier: Development Status :: 5 - Production/Stable
Classifier: License :: OSI Approved :: MIT License
Classifier: Intended Audience :: Developers
Classifier: Natural Language :: English
Classifier: Operating System :: OS Independent
Classifier: Programming Language :: Python :: 3.8
Classifier: Programming Language :: Python :: 3.9
Classifier: Topic :: Internet
Classifier: Topic :: Software Development :: Libraries
Classifier: Topic :: Software Development :: Libraries :: Python Modules
Classifier: Topic :: Utilities
Classifier: Typing :: Typed
Requires-Python: >=3.8.0
Provides-Extra: docs
Provides-Extra: voice
Provides-Extra: speed
